LICENSE
README.md
setup.cfg
setup.py
swissql/__init__.py
swissql/__main__.py
swissql/main.py
swissql/manifest.py
swissql.egg-info/PKG-INFO
swissql.egg-info/SOURCES.txt
swissql.egg-info/dependency_links.txt
swissql.egg-info/entry_points.txt
swissql.egg-info/requires.txt
swissql.egg-info/top_level.txt
swissql/analyzers/__init__.py
swissql/analyzers/anti_pattern/__init__.py
swissql/analyzers/anti_pattern/anti_pattern_finder.py
swissql/analyzers/optimizations/__init__.py
swissql/analyzers/optimizations/dynamic_optimizer.py
swissql/analyzers/optimizations/static_optimizer.py
swissql/analyzers/rule_checker/__init__.py
swissql/analyzers/rule_checker/custom_rule.py
swissql/analyzers/rule_checker/rule_finder.py
swissql/analyzers/rule_checker/sql_finder.py
swissql/analyzers/rule_checker/tree_pattern_find.py
swissql/analyzers/rule_checker/grammar/__init__.py
swissql/analyzers/style/__init__.py
swissql/analyzers/style/sql_formatter.py
swissql/analyzers/style/sql_style_error.py
swissql/analyzers/syntax/__init__.py
swissql/analyzers/syntax/sql_parser.py
swissql/utils/__init__.py
swissql/utils/argument_parser.py
swissql/utils/exceptions.py
swissql/utils/formatter.py
swissql/utils/schema_reader.py