Metadata-Version: 2.1
Name: swissql
Version: 0.2.5.1
Summary: Spark SQL analytic engine
Home-page: https://github.com/IPROSpark/SparkSQL-Analyzer
Author: husker Nicialy Quakumei
Author-email: andrey24072002@bk.ru
License: GNU
Platform: UNKNOWN
Requires-Python: >=3.7.*
License-File: LICENSE
